{
    "key": "group_60ed3f8408a2e",
    "title": "Block: Hero Fleet",
    "fields": [
        {
            "key": "field_60ed4fd81a059",
            "label": "Type of hero",
            "name": "type_of_hero",
            "type": "radio",
            "instructions": "",
            "required": 0,
            "conditional_logic": 0,
            "wrapper": {
                "width": "",
                "class": "",
                "id": ""
            },
            "choices": {
                "single": "Single",
                "multiple": "Slider"
            },
            "allow_null": 0,
            "other_choice": 0,
            "default_value": "",
            "layout": "horizontal",
            "return_format": "value",
            "save_other_choice": 0
        },
        {
            "key": "field_60f0565ad0b2b",
            "label": "Fleet hero subtitle",
            "name": "fleet_hero_subtitle",
            "type": "text",
            "instructions": "",
            "required": 0,
            "conditional_logic": [
                [
                    {
                        "field": "field_60ed4fd81a059",
                        "operator": "==",
                        "value": "single"
                    }
                ]
            ],
            "wrapper": {
                "width": "50",
                "class": "",
                "id": ""
            },
            "default_value": "",
            "placeholder": "",
            "prepend": "",
            "append": "",
            "maxlength": ""
        },
        {
            "key": "field_60f003601baa4",
            "label": "Fleet hero title mobile",
            "name": "title_mobile",
            "type": "text",
            "instructions": "",
            "required": 0,
            "conditional_logic": [
                [
                    {
                        "field": "field_60ed4fd81a059",
                        "operator": "==",
                        "value": "multiple"
                    }
                ]
            ],
            "wrapper": {
                "width": "33",
                "class": "",
                "id": ""
            },
            "default_value": "",
            "placeholder": "",
            "prepend": "",
            "append": "",
            "maxlength": ""
        },
        {
            "key": "field_60f003047fa6e",
            "label": "Fleet hero nav title desktop",
            "name": "title_desktop",
            "type": "text",
            "instructions": "",
            "required": 0,
            "conditional_logic": [
                [
                    {
                        "field": "field_60ed4fd81a059",
                        "operator": "==",
                        "value": "multiple"
                    }
                ]
            ],
            "wrapper": {
                "width": "33",
                "class": "",
                "id": ""
            },
            "default_value": "",
            "placeholder": "",
            "prepend": "",
            "append": "",
            "maxlength": ""
        },
        {
            "key": "field_60f81d532979b",
            "label": "Fleet hero active slide",
            "name": "active_slide",
            "type": "text",
            "instructions": "Copy the content of the \"Slide nav name\" field here to make it active.",
            "required": 0,
            "conditional_logic": [
                [
                    {
                        "field": "field_60ed4fd81a059",
                        "operator": "==",
                        "value": "multiple"
                    }
                ]
            ],
            "wrapper": {
                "width": "33",
                "class": "",
                "id": ""
            },
            "default_value": "",
            "placeholder": "",
            "prepend": "",
            "append": "",
            "maxlength": ""
        },
        {
            "key": "field_60ed4087126f7",
            "label": "Fleet slider",
            "name": "fleet_slider",
            "type": "repeater",
            "instructions": "",
            "required": 0,
            "conditional_logic": [
                [
                    {
                        "field": "field_60ed4fd81a059",
                        "operator": "==",
                        "value": "multiple"
                    }
                ]
            ],
            "wrapper": {
                "width": "",
                "class": "",
                "id": ""
            },
            "collapsed": "",
            "min": 0,
            "max": 0,
            "layout": "block",
            "button_label": "",
            "sub_fields": [
                {
                    "key": "field_60ed3fb6126f0",
                    "label": "Slide title",
                    "name": "slide_title",
                    "type": "textarea",
                    "instructions": "",
                    "required": 0,
                    "conditional_logic": 0,
                    "wrapper": {
                        "width": "33",
                        "class": "",
                        "id": ""
                    },
                    "default_value": "",
                    "placeholder": "",
                    "maxlength": "",
                    "rows": "",
                    "new_lines": "br"
                },
                {
                    "key": "field_60ed3fbc126f1",
                    "label": "Slide description",
                    "name": "slide_description",
                    "type": "textarea",
                    "instructions": "",
                    "required": 0,
                    "conditional_logic": 0,
                    "wrapper": {
                        "width": "33",
                        "class": "",
                        "id": ""
                    },
                    "default_value": "",
                    "placeholder": "",
                    "maxlength": "",
                    "rows": "",
                    "new_lines": "br"
                },
                {
                    "key": "field_60ed440dc81c3",
                    "label": "Slide nav name",
                    "name": "slide_nav_name",
                    "type": "text",
                    "instructions": "",
                    "required": 0,
                    "conditional_logic": 0,
                    "wrapper": {
                        "width": "33",
                        "class": "",
                        "id": ""
                    },
                    "default_value": "",
                    "placeholder": "",
                    "prepend": "",
                    "append": "",
                    "maxlength": ""
                },
                {
                    "key": "field_60ed3fe1126f2",
                    "label": "Customer group",
                    "name": "customer_group",
                    "type": "group",
                    "instructions": "",
                    "required": 0,
                    "conditional_logic": 0,
                    "wrapper": {
                        "width": "100",
                        "class": "",
                        "id": ""
                    },
                    "layout": "block",
                    "sub_fields": [
                        {
                            "key": "field_60ed3ffc126f4",
                            "label": "Customer title",
                            "name": "customer_title",
                            "type": "textarea",
                            "instructions": "",
                            "required": 0,
                            "conditional_logic": 0,
                            "wrapper": {
                                "width": "25",
                                "class": "",
                                "id": ""
                            },
                            "default_value": "",
                            "placeholder": "",
                            "maxlength": "",
                            "rows": 4,
                            "new_lines": ""
                        },
                        {
                            "key": "field_60ed400c126f5",
                            "label": "Customer name",
                            "name": "customer_name",
                            "type": "textarea",
                            "instructions": "",
                            "required": 0,
                            "conditional_logic": 0,
                            "wrapper": {
                                "width": "25",
                                "class": "",
                                "id": ""
                            },
                            "default_value": "",
                            "placeholder": "",
                            "maxlength": "",
                            "rows": 4,
                            "new_lines": ""
                        },
                        {
                            "key": "field_60ed4020126f6",
                            "label": "Customer desc",
                            "name": "customer_desc",
                            "type": "textarea",
                            "instructions": "",
                            "required": 0,
                            "conditional_logic": 0,
                            "wrapper": {
                                "width": "25",
                                "class": "",
                                "id": ""
                            },
                            "default_value": "",
                            "placeholder": "",
                            "maxlength": "",
                            "rows": 4,
                            "new_lines": ""
                        },
                        {
                            "key": "field_60ed3ff1126f3",
                            "label": "Customer image",
                            "name": "customer_image",
                            "type": "image",
                            "instructions": "",
                            "required": 0,
                            "conditional_logic": 0,
                            "wrapper": {
                                "width": "25",
                                "class": "",
                                "id": ""
                            },
                            "return_format": "array",
                            "preview_size": "medium",
                            "library": "all",
                            "min_width": "",
                            "min_height": "",
                            "min_size": "",
                            "max_width": "",
                            "max_height": "",
                            "max_size": "",
                            "mime_types": ""
                        }
                    ]
                }
            ]
        },
        {
            "key": "field_60ed50221a05a",
            "label": "Fleet hero",
            "name": "fleet_hero",
            "type": "group",
            "instructions": "",
            "required": 0,
            "conditional_logic": [
                [
                    {
                        "field": "field_60ed4fd81a059",
                        "operator": "==",
                        "value": "single"
                    }
                ]
            ],
            "wrapper": {
                "width": "100",
                "class": "",
                "id": ""
            },
            "layout": "block",
            "sub_fields": [
                {
                    "key": "field_60f57d5285b4f",
                    "label": "Hero name",
                    "name": "hero_name",
                    "type": "text",
                    "instructions": "",
                    "required": 0,
                    "conditional_logic": 0,
                    "wrapper": {
                        "width": "",
                        "class": "",
                        "id": ""
                    },
                    "default_value": "",
                    "placeholder": "",
                    "prepend": "",
                    "append": "",
                    "maxlength": ""
                },
                {
                    "key": "field_60ed50a11a066",
                    "label": "Hero title",
                    "name": "hero_title",
                    "type": "text",
                    "instructions": "",
                    "required": 0,
                    "conditional_logic": 0,
                    "wrapper": {
                        "width": "50",
                        "class": "",
                        "id": ""
                    },
                    "default_value": "",
                    "placeholder": "",
                    "prepend": "",
                    "append": "",
                    "maxlength": ""
                },
                {
                    "key": "field_60ed50af1a067",
                    "label": "Hero description",
                    "name": "hero_description",
                    "type": "textarea",
                    "instructions": "",
                    "required": 0,
                    "conditional_logic": 0,
                    "wrapper": {
                        "width": "50",
                        "class": "",
                        "id": ""
                    },
                    "default_value": "",
                    "placeholder": "",
                    "maxlength": "",
                    "rows": "",
                    "new_lines": ""
                },
                {
                    "key": "field_60ed50351a05b",
                    "label": "Customer group",
                    "name": "customer_group",
                    "type": "group",
                    "instructions": "",
                    "required": 0,
                    "conditional_logic": 0,
                    "wrapper": {
                        "width": "100",
                        "class": "",
                        "id": ""
                    },
                    "layout": "block",
                    "sub_fields": [
                        {
                            "key": "field_60ed50351a05c",
                            "label": "Customer title",
                            "name": "customer_title",
                            "type": "text",
                            "instructions": "",
                            "required": 0,
                            "conditional_logic": 0,
                            "wrapper": {
                                "width": "25",
                                "class": "",
                                "id": ""
                            },
                            "default_value": "",
                            "placeholder": "",
                            "prepend": "",
                            "append": "",
                            "maxlength": ""
                        },
                        {
                            "key": "field_60ed50351a05d",
                            "label": "Customer name",
                            "name": "customer_name",
                            "type": "text",
                            "instructions": "",
                            "required": 0,
                            "conditional_logic": 0,
                            "wrapper": {
                                "width": "25",
                                "class": "",
                                "id": ""
                            },
                            "default_value": "",
                            "placeholder": "",
                            "prepend": "",
                            "append": "",
                            "maxlength": ""
                        },
                        {
                            "key": "field_60ed50351a05e",
                            "label": "Customer desc",
                            "name": "customer_desc",
                            "type": "text",
                            "instructions": "",
                            "required": 0,
                            "conditional_logic": 0,
                            "wrapper": {
                                "width": "25",
                                "class": "",
                                "id": ""
                            },
                            "default_value": "",
                            "placeholder": "",
                            "prepend": "",
                            "append": "",
                            "maxlength": ""
                        },
                        {
                            "key": "field_60ed50351a05f",
                            "label": "Customer image",
                            "name": "customer_image",
                            "type": "image",
                            "instructions": "",
                            "required": 0,
                            "conditional_logic": 0,
                            "wrapper": {
                                "width": "25",
                                "class": "",
                                "id": ""
                            },
                            "return_format": "array",
                            "preview_size": "medium",
                            "library": "all",
                            "min_width": "",
                            "min_height": "",
                            "min_size": "",
                            "max_width": "",
                            "max_height": "",
                            "max_size": "",
                            "mime_types": ""
                        }
                    ]
                }
            ]
        }
    ],
    "location": [
        [
            {
                "param": "block",
                "operator": "==",
                "value": "acf\/hero-fleet"
            }
        ]
    ],
    "menu_order": 0,
    "position": "normal",
    "style": "default",
    "label_placement": "top",
    "instruction_placement": "label",
    "hide_on_screen": "",
    "active": true,
    "description": "",
    "modified": 1626944178
}